piredactor/__init__.py
piredactor/config.py
piredactor/decorator.py
piredactor/pii_config.json
piredactor/redactor.py
piredactor-0.1.5.dist-info/licenses/LICENSE
piredactor-0.1.5.dist-info/METADATA
piredactor-0.1.5.dist-info/WHEEL
piredactor-0.1.5.dist-info/top_level.txt
piredactor-0.1.5.dist-info/RECORD
