Metadata-Version: 2.4
Name: piredactor
Version: 0.1.5
Summary: A flexible Python package for redacting Personally Identifiable Information (PII) from dictionaries and lists using a schema-based approach.
Author: Piyush Chauhan
Author-email: Piyush Chauhan <piyush23321@gmail.com>
License: MIT License
Keywords: pii,redact,privacy,decorator,schema,gdpr,security
Classifier: Development Status :: 4 - Beta
Classifier: Intended Audience :: Developers
Classifier: License :: OSI Approved :: MIT License
Classifier: Programming Language :: Python :: 3
Classifier: Programming Language :: Python :: 3.7
Classifier: Programming Language :: Python :: 3.8
Classifier: Programming Language :: Python :: 3.9
Classifier: Programming Language :: Python :: 3.10
Classifier: Programming Language :: Python :: 3.11
Classifier: Operating System :: OS Independent
Classifier: Topic :: Security
Classifier: Topic :: Software Development :: Libraries :: Python Modules
Requires-Python: >=3.7
License-File: LICENSE
Requires-Dist: PyYAML>=5.0
Dynamic: license-file
